{
    "track": {
        "album": {
            "id": "0BFzNaeaNv4mahOzwZFGHK",
            "name": "Royal Blood"
        },
        "artists": [
            {
                "id": "2S5hlvw4CMtMGswFtfdK15",
                "name": "Royal Blood"
            }
        ],
        "id": "3MjrueDQKVr6xDDseZwhEd",
        "name": "Figure It Out",
        "popularity": 69,
        "danceability": 0.658,
        "energy": 0.814,
        "acousticness": 0.229,
        "instrumentalness": 0.00676,
        "valence": 0.69
    }
}